py4tga/__init__.py
py4tga/py4tga.py
py4tga-0.1.0.dist-info/AUTHORS.md
py4tga-0.1.0.dist-info/LICENSE
py4tga-0.1.0.dist-info/METADATA
py4tga-0.1.0.dist-info/WHEEL
py4tga-0.1.0.dist-info/RECORD
