Metadata-Version: 2.1
Name: py4tga
Version: 0.1.0
Summary: Python for thermogravimetry analysis
License: MIT
Author: Rahul Ramesh Nair
Requires-Python: >=3.10,<4.0
Classifier: License :: OSI Approved :: MIT License
Classifier: Programming Language :: Python :: 3
Classifier: Programming Language :: Python :: 3.10
Classifier: Programming Language :: Python :: 3.11
Classifier: Programming Language :: Python :: 3.12
Requires-Dist: ipykernel (>=6.29.4,<7.0.0)
Requires-Dist: numpy (>=1.26.4,<2.0.0)
Requires-Dist: pandas (>=2.2.2,<3.0.0)
Requires-Dist: pip (>=23.3.1,<24.0.0)
Requires-Dist: scipy (>=1.13.0,<2.0.0)
